django_jalalify/__init__.py
django_jalalify/apps.py
django_jalalify/fields.py
django_jalalify/filters.py
django_jalalify/functions.py
django_jalalify/mixins.py
django_jalalify/tests.py
django_jalalify/timezone.py
django_jalalify/utils.py
django_jalalify/admin/__init__.py
django_jalalify/admin/filters.py
django_jalalify/migrations/__init__.py
django_jalalify/templatetags/__init__.py
django_jalalify/templatetags/rangefilter_compat.py
django_jalalify-1.2.0.dist-info/METADATA
django_jalalify-1.2.0.dist-info/WHEEL
django_jalalify-1.2.0.dist-info/top_level.txt
django_jalalify-1.2.0.dist-info/RECORD
