Metadata-Version: 2.1
Name: django-jalalify
Version: 1.2.0
Summary: Pluggable django app to provide some utilities for jalali solar calendar for your Django projects.
Home-page: https://github.com/javadnikbakht/django-jalalify
Author: Mohammad Javad Nikbakht
Author-email: javadnikbakht@mail.com
License: GNU General Public License v3 (GPLv3)
Classifier: Environment :: Web Environment
Classifier: Framework :: Django
Classifier: Framework :: Django :: 3.0
Classifier: Framework :: Django :: 3.1
Classifier: Framework :: Django :: 3.2
Classifier: Framework :: Django :: 4.0
Classifier: Framework :: Django :: 4.1
Classifier: Framework :: Django :: 4.2
Classifier: Intended Audience :: Developers
Classifier: License :: OSI Approved :: BSD License
Classifier: Operating System :: OS Independent
Classifier: Programming Language :: Python
Classifier: Programming Language :: Python :: 3
Classifier: Programming Language :: Python :: 3 :: Only
Classifier: Programming Language :: Python :: 3.8
Classifier: Programming Language :: Python :: 3.9
Classifier: Programming Language :: Python :: 3.10
Classifier: Programming Language :: Python :: 3.11
Classifier: Topic :: Internet :: WWW/HTTP
Classifier: Topic :: Internet :: WWW/HTTP :: Dynamic Content
Requires-Python: >=3.8
Requires-Dist: django (>=3.0)
Requires-Dist: djangorestframework (>=3.11.0)
Requires-Dist: django-filter (>=2.3.0)
Requires-Dist: khayyam (>=3.0.17)
Requires-Dist: pytz (>=2023.3)
